doc/Makefile
doc/adb.rst
doc/api.in
doc/cli.rst
doc/conf.py
doc/config.rst
doc/dev.rst
doc/estat.rst
doc/giz.rst
doc/iamc.rst
doc/index.rst
doc/ipcc.rst
doc/iso.rst
doc/itdp.rst
doc/jrc.rst
doc/oica.rst
doc/org.rst
doc/proto.rst
doc/report.rst
doc/roadmap.rst
doc/standards.rst
doc/store.rst
doc/testing.rst
doc/tests.rst
doc/usage.rst
doc/util.rst
doc/whatsnew.rst
doc/_static/logo.png
doc/_static/css/custom.css
doc/_template/autosummary/class.rst
doc/_template/autosummary/module.rst
doc/howto/cli-edit.rst
doc/howto/data-csv.rst
doc/howto/index.rst
doc/howto/metadata.rst
transport_data/__init__.py
transport_data/__main__.py
transport_data/config.py
transport_data/report.py
transport_data/store.py
transport_data/testing.py
transport_data/adb/__init__.py
transport_data/adb/cli.py
transport_data/cli/__init__.py
transport_data/cli/interactive.py
transport_data/data/template/metadata-attribute-0.rst
transport_data/data/template/metadata-set-0.rst
transport_data/data/template/metadata-set-1.html
transport_data/data/template/metadata-set-1.rst
transport_data/data/template/metadata-set-2.html
transport_data/data/template/odt-styles.xml
transport_data/data/tests/iamc.csv
transport_data/data/tests/metadata-input.xlsx
transport_data/data/tests/read-csv-0.csv
transport_data/data/tests/read-csv-1.csv
transport_data/data/tests/read-csv-2.xlsx
transport_data/data/tests/ckan/package.json
transport_data/data/tests/itdp/rtdb.xlsx
transport_data/estat/__init__.py
transport_data/iamc/__init__.py
transport_data/iamc/cli.py
transport_data/ipcc/__init__.py
transport_data/ipcc/structure.py
transport_data/iso/__init__.py
transport_data/iso/cli.py
transport_data/itdp/__init__.py
transport_data/itdp/cli.py
transport_data/itdp/rtdb.py
transport_data/jrc/__init__.py
transport_data/jrc/cli.py
transport_data/oica/__init__.py
transport_data/oica/cli.py
transport_data/oica/registry.json
transport_data/org/__init__.py
transport_data/org/ckan.py
transport_data/org/cli.py
transport_data-24.12.29.dist-info/LICENSE
transport_data-24.12.29.dist-info/METADATA
transport_data-24.12.29.dist-info/WHEEL
transport_data-24.12.29.dist-info/entry_points.txt
transport_data-24.12.29.dist-info/top_level.txt
transport_data-24.12.29.dist-info/RECORD
