Metadata-Version: 2.1
Name: transport-data
Version: 24.12.29
Summary: Tools for the Transport Data Commons
Author: Transport Data Commons Initiative (TDCI)
Maintainer-email: Paul Natsuo Kishimoto <mail@paul.kishimoto.name>
Project-URL: homepage, https://transport-data.org
Project-URL: repository, https://github.com/transport-data/tools
Classifier: Operating System :: OS Independent
Classifier: Programming Language :: Python
Classifier: Programming Language :: Python :: 3
Classifier: Programming Language :: Python :: 3.9
Classifier: Programming Language :: Python :: 3.10
Classifier: Programming Language :: Python :: 3.11
Classifier: Programming Language :: Python :: 3.12
Classifier: Programming Language :: Python :: 3.13
Requires-Python: >=3.9
License-File: LICENSE
Requires-Dist: ckanapi
Requires-Dist: click
Requires-Dist: docutils
Requires-Dist: dsss[git-store]>=1.3.0
Requires-Dist: Jinja2
Requires-Dist: openpyxl
Requires-Dist: packaging
Requires-Dist: pandas
Requires-Dist: platformdirs
Requires-Dist: pluggy
Requires-Dist: pooch
Requires-Dist: prompt-toolkit
Requires-Dist: pycountry
Requires-Dist: requests
Requires-Dist: sdmx1>=2.9
Requires-Dist: tqdm
Provides-Extra: docs
Requires-Dist: furo; extra == "docs"
Requires-Dist: Sphinx; extra == "docs"
Requires-Dist: sphinx-autorun; extra == "docs"
Provides-Extra: google
Requires-Dist: google-api-python-client; extra == "google"
Requires-Dist: google-auth-httplib2; extra == "google"
Requires-Dist: google-auth-oauthlib; extra == "google"
Provides-Extra: tests
Requires-Dist: pytest; extra == "tests"
Requires-Dist: pytest-cov; extra == "tests"
Requires-Dist: pytest-rerunfailures; extra == "tests"
Requires-Dist: pytest-timeout; extra == "tests"
Requires-Dist: pytest-xdist; extra == "tests"
Requires-Dist: transport-data[google]; extra == "tests"
